Metadata-Version: 1.0
Name: Warframepip
Version: 1.0
Summary: Warframe Modules. WORK IN PROGRESS!
Home-page: http://pymbook.readthedocs.org/en/latest/
Author: Blake Thompson
Author-email: blakethompsonbat@gmail.com
License: MIT
Platform: Linux
Platform: Windows
Platform: MacOS
